pz_clouder/__init__.py
pz_clouder/_version.py
pz_clouder/pz_aws_cloudwatch.py
pz_clouder/pz_aws_ec2.py
pz_clouder/pz_aws_master.py
pz_clouder/pz_aws_s3.py
pz_clouder/pz_aws_sqs.py
pz_clouder-0.0.2.dist-info/LICENSE
pz_clouder-0.0.2.dist-info/METADATA
pz_clouder-0.0.2.dist-info/WHEEL
pz_clouder-0.0.2.dist-info/top_level.txt
pz_clouder-0.0.2.dist-info/RECORD
