Metadata-Version: 2.1
Name: pz-clouder
Version: 0.0.2
Summary: Cloud wrapper for ML workloads
Author-email: PrismaPhotonics <evgeny.ilievsky@prismaphotonics.com>
License: Apache-2.0
Project-URL: Issues, https://github.com/PrismaPhotonics/pz-clouder/issues
Project-URL: Source, https://github.com/PrismaPhotonics/pz-clouder
Classifier: Programming Language :: Python :: 3
Classifier: Programming Language :: Python :: 3.8
Classifier: Programming Language :: Python :: 3.9
Classifier: Programming Language :: Python :: 3.10
Classifier: Programming Language :: Python :: 3.11
Classifier: Programming Language :: Python :: 3.12
Classifier: Development Status :: 2 - Pre-Alpha
Requires-Python: >=3.8
License-File: LICENSE
Provides-Extra: tests
Requires-Dist: pytest==8.3.4; extra == "tests"
Requires-Dist: pytest-sugar==1.0.0; extra == "tests"
Requires-Dist: pytest-cov==3.0.0; extra == "tests"
Requires-Dist: pytest-mock==3.8.2; extra == "tests"
Provides-Extra: dev
Requires-Dist: pz-clouder[tests]; extra == "dev"
